[
null,
{"id":1,"expanded":true,"name":"Ilha","order":1,"parentId":0,"scrollX":1965.6,"scrollY":1096.8},
{"id":2,"expanded":true,"name":"porto","order":6,"parentId":1,"scrollX":2838.5454545454545,"scrollY":2092.3636363636365},
{"id":3,"expanded":true,"name":"vila_direita","order":5,"parentId":1,"scrollX":2780.727272727273,"scrollY":1566.5454545454545},
{"id":4,"expanded":true,"name":"vila_inf_esquerda","order":2,"parentId":1,"scrollX":2661.6,"scrollY":3754.7999999999997},
{"id":5,"expanded":false,"name":"vila_sup_esquerdo","order":4,"parentId":1,"scrollX":2433,"scrollY":1701},
{"id":6,"expanded":true,"name":"floresta_central_inf","order":7,"parentId":1,"scrollX":1965.6,"scrollY":1086},
{"id":7,"expanded":false,"name":"vila_central","order":13,"parentId":1,"scrollX":816,"scrollY":980},
{"id":8,"expanded":false,"name":"floresta_central_sup","order":14,"parentId":1,"scrollX":3429.6,"scrollY":1994.3999999999999},
{"id":9,"expanded":true,"name":"Salão Principal","order":9,"parentId":6,"scrollX":1965.6,"scrollY":1086},
null,
{"id":11,"expanded":true,"name":"Corredor Esquerdo","order":10,"parentId":9,"scrollX":1965.6,"scrollY":1086},
{"id":12,"expanded":true,"name":"Dungeon Esquerda","order":11,"parentId":11,"scrollX":1965.6,"scrollY":1086},
{"id":13,"expanded":false,"name":"Dungeo Esquerda_b","order":12,"parentId":12,"scrollX":811,"scrollY":699.5},
{"id":14,"expanded":true,"name":"Casa Wulfhilda","order":3,"parentId":4,"scrollX":819,"scrollY":452.5},
{"id":15,"expanded":false,"name":"Casa Velinha","order":8,"parentId":6,"scrollX":1965.6,"scrollY":1086}
]